keybeat/__init__.py
keybeat/__main__.py
keybeat/cli.py
keybeat/create.py
keybeat/utils.py
keybeat/validate.py
keybeat-0.1.0.dist-info/LICENSE
keybeat-0.1.0.dist-info/METADATA
keybeat-0.1.0.dist-info/WHEEL
keybeat-0.1.0.dist-info/entry_points.txt
keybeat-0.1.0.dist-info/RECORD
